mynameisuncle
